prodigy_cryst/__init__.py
prodigy_cryst/classify.py
prodigy_cryst/data/List_of_features-MANY.csv
prodigy_cryst/data/classifier.sav
prodigy_cryst/interface_classifier.py
prodigy_cryst/lib/__init__.py
prodigy_cryst/lib/aa_properties.py
prodigy_cryst/lib/parsers.py
prodigy_cryst/lib/utils.py
prodigy_cryst-1.0.1.dist-info/LICENSE
prodigy_cryst-1.0.1.dist-info/METADATA
prodigy_cryst-1.0.1.dist-info/WHEEL
prodigy_cryst-1.0.1.dist-info/entry_points.txt
prodigy_cryst-1.0.1.dist-info/RECORD
