Metadata-Version: 2.1
Name: prodigy-cryst
Version: 1.0.1
Summary: Predicts if a protein complex interface is biological or crystallographic.
License: Apache-2.0
Author: BonvinLab
Author-email: bonvinlab.support@uu.nl
Requires-Python: >=3.8,<4.0
Classifier: Development Status :: 5 - Production/Stable
Classifier: Intended Audience :: Science/Research
Classifier: License :: OSI Approved :: Apache Software License
Classifier: Programming Language :: Python :: 3
Classifier: Programming Language :: Python :: 3.8
Classifier: Programming Language :: Python :: 3.9
Classifier: Programming Language :: Python :: 3.10
Classifier: Programming Language :: Python :: 3.11
Classifier: Programming Language :: Python :: 3.12
Classifier: Topic :: Scientific/Engineering :: Bio-Informatics
Classifier: Topic :: Scientific/Engineering :: Chemistry
Requires-Dist: biopython (>=1.79,<2.0)
Requires-Dist: numpy (>=1.20,<1.21)
Requires-Dist: scikit-learn (==0.22)
